gitignore_filter/__init__.py
gitignore_filter/core.py
gitignore_filter/logging.py
gitignore_filter/config/__init__.py
gitignore_filter/config/git.py
gitignore_filter/patterns/__init__.py
gitignore_filter/patterns/base.py
gitignore_filter/patterns/pathspec.py
gitignore_filter/scanner/__init__.py
gitignore_filter/scanner/base.py
gitignore_filter/scanner/fs.py
gitignore_filter/scanner/ignore.py
gitignore_filter/scanner/worker.py
gitignore_filter/utils/__init__.py
gitignore_filter/utils/cache.py
gitignore_filter/utils/path.py
gitignore_filter/utils/pathspec_util.py
gitignore_filter-0.2.3.dist-info/METADATA
gitignore_filter-0.2.3.dist-info/WHEEL
gitignore_filter-0.2.3.dist-info/licenses/LICENSE
gitignore_filter-0.2.3.dist-info/RECORD
